<?xml version="1.0" encoding="UTF-8"?>

<databaseChangeLog
        xmlns="http://www.liquibase.org/xml/ns/dbchangelog"
        xmlns:xsi="http://www.w3.org/2001/XMLSchema-instance"
        xsi:schemaLocation="http://www.liquibase.org/xml/ns/dbchangelog
         http://www.liquibase.org/xml/ns/dbchangelog/dbchangelog-3.1.xsd">




    <changeSet author="elena_oshkina" id="insert_chain_task_for_mini_games">
        <insert tableName="mini_games">
            <column name="note"
                    value="{&quot;data&quot;:[&quot;.txt&quot;,&quot;://&quot;,&quot;http&quot;,&quot;circ&quot;,&quot;/&quot;,&quot;.org&quot;,&quot;slon&quot;]}"/>
            <column name="id" value="3"/>
            <column name="parent_id" value="0"/>
            <column name="child_id" value="0"/>
            <column name="type_id" value="2"/>
            <column name="step_id" value="52"/>
        </insert>

    </changeSet>
    <changeSet author="elena_oshkina" id="insert_chain_answers_for_mini_games">
        <insert tableName="answers_on_chain">
            <column name="answer" value="{&quot;data&quot;:[&quot;http&quot;,&quot;://&quot;,&quot;circ&quot;,&quot;.org&quot;,&quot;/&quot;,&quot;slon&quot;,&quot;.txt&quot;]}"/>
            <column name="game_id" value="3"/>
        </insert>

    </changeSet>

    <!--<changeSet author="dmitrii_borodin" id="insert_chain_task_for_mini_games">-->
        <!--<insert tableName="mini_games">-->
            <!--<column name="note"-->
                    <!--value="{&quot;data&quot;:[&quot;Непрерывный&quot;, &quot;сигнал&quot;, &quot;принимает&quot;, &quot;бесконечное&quot;, &quot;множество&quot;, &quot;значений&quot;, &quot;из&quot;, &quot;некоторого&quot;, &quot;диапазона&quot;, &quot;,а&quot;, &quot;значения&quot;, &quot;дискретного&quot;, &quot;сигнала&quot;, &quot;можно&quot;, &quot;представить&quot;, &quot;целыми&quot;, &quot;числами&quot;]}"/>-->
            <!--<column name="id" value="4"/>-->
            <!--<column name="parent_id" value="0"/>-->
            <!--<column name="child_id" value="0"/>-->
            <!--<column name="type_id" value="2"/>-->
            <!--<column name="step_id" value="53"/>-->
        <!--</insert>-->

    <!--</changeSet>-->
    <!--<changeSet author="dmitrii_borodin" id="insert_chain_answers_for_mini_games">-->
        <!--<insert tableName="answers_on_chain">-->
            <!--<column name="answer" value="{&quot;data&quot;:[&quot;Непрерывный&quot;, &quot;сигнал&quot;, &quot;принимает&quot;, &quot;бесконечное&quot;, &quot;множество&quot;, &quot;значений&quot;, &quot;из&quot;, &quot;некоторого&quot;, &quot;диапазона&quot;, &quot;,а&quot;, &quot;значения&quot;, &quot;дискретного&quot;, &quot;сигнала&quot;, &quot;можно&quot;, &quot;представить&quot;, &quot;целыми&quot;, &quot;числами&quot;]}"/>-->
            <!--<column name="game_id" value="4"/>-->
        <!--</insert>-->

    <!--</changeSet>-->
</databaseChangeLog>